cli/__init__.py
cli/__main__.py
cli/_version.py
cli/commands/__init__.py
cli/commands/cli.py
cli/commands/plugin.py
cli/commands/sync.py
cli/commands/term.py
cli/commands/workflow.py
cli/core/__init__.py
cli/core/api_client.py
cli/core/config.py
cli/core/env_config.py
cli/core/shared.py
cli/gui/__init__.py
cli/gui/base.py
cli/gui/file_browser.py
cli/gui/login.py
cli/gui/main.py
cli/gui/utilities.py
config/rediacc-cli-term-config.json
config/rediacc-cli.json
config/rediacc-gui-config.json
config/rediacc-gui-translations.json
rediacc_cli-0.1.23.dist-info/METADATA
rediacc_cli-0.1.23.dist-info/WHEEL
rediacc_cli-0.1.23.dist-info/entry_points.txt
rediacc_cli-0.1.23.dist-info/top_level.txt
rediacc_cli-0.1.23.dist-info/RECORD
