Metadata-Version: 2.4
Name: rediacc-cli
Version: 0.1.23
Summary: Rediacc CLI - Command-line interface for Rediacc distributed task execution system
Author-email: Rediacc Team <info@rediacc.com>
Maintainer-email: Rediacc Team <info@rediacc.com>
Project-URL: Homepage, https://rediacc.com
Project-URL: Documentation, https://docs.rediacc.com
Project-URL: Repository, https://github.com/rediacc/cli
Project-URL: Bug Tracker, https://github.com/rediacc/cli/issues
Keywords: rediacc,cli,distributed,task-execution,ssh,automation,devops,infrastructure
Classifier: Development Status :: 4 - Beta
Classifier: Intended Audience :: Developers
Classifier: Intended Audience :: System Administrators
Classifier: Topic :: Software Development :: Build Tools
Classifier: Topic :: System :: Systems Administration
Classifier: Topic :: Utilities
Classifier: Programming Language :: Python :: 3
Classifier: Programming Language :: Python :: 3.8
Classifier: Programming Language :: Python :: 3.9
Classifier: Programming Language :: Python :: 3.10
Classifier: Programming Language :: Python :: 3.11
Classifier: Programming Language :: Python :: 3.12
Classifier: Operating System :: OS Independent
Classifier: Operating System :: POSIX :: Linux
Classifier: Operating System :: MacOS
Classifier: Operating System :: Microsoft :: Windows
Classifier: Environment :: Console
Requires-Python: >=3.8
Requires-Dist: cryptography>=41.0.0
Requires-Dist: requests>=2.31.0
Requires-Dist: pyotp>=2.9.0
Provides-Extra: dev
Requires-Dist: pytest>=7.0; extra == "dev"
Requires-Dist: pytest-cov>=4.0; extra == "dev"
Requires-Dist: black>=23.0; extra == "dev"
Requires-Dist: flake8>=6.0; extra == "dev"
Requires-Dist: mypy>=1.0; extra == "dev"
Requires-Dist: build>=0.10; extra == "dev"
Requires-Dist: twine>=4.0; extra == "dev"
Provides-Extra: test
Requires-Dist: pytest>=7.0; extra == "test"
Requires-Dist: pytest-cov>=4.0; extra == "test"
Requires-Dist: pyyaml>=6.0; extra == "test"
